mt5_server/__init__.py
mt5_server/__main__.py
mt5_server/server.py
mt5_server-0.0.5.dist-info/LICENSE
mt5_server-0.0.5.dist-info/LICENSE.txt
mt5_server-0.0.5.dist-info/METADATA
mt5_server-0.0.5.dist-info/WHEEL
mt5_server-0.0.5.dist-info/top_level.txt
mt5_server-0.0.5.dist-info/RECORD
