Metadata-Version: 2.1
Name: mt5-server
Version: 0.0.5
Summary: Servidor
Home-page: https://github.com/michelmetran/mt5_server
Author: Michel Metran
Author-email: michelmetran@gmail.com
Keywords: python,metatrader
Classifier: Programming Language :: Python :: 3
Classifier: License :: OSI Approved :: MIT License
Classifier: Operating System :: OS Independent
Classifier: Natural Language :: Portuguese
Classifier: Intended Audience :: Developers
Requires-Python: >=3
License-File: LICENSE
License-File: LICENSE.txt
Requires-Dist: plumbum
Requires-Dist: pyparsing
Requires-Dist: rpyc
